pymeanings/__init__.py
pymeanings/command_line.py
pymeanings/meaning.py
pymeanings-0.1.dist-info/METADATA
pymeanings-0.1.dist-info/WHEEL
pymeanings-0.1.dist-info/entry_points.txt
pymeanings-0.1.dist-info/top_level.txt
pymeanings-0.1.dist-info/RECORD
