Metadata-Version: 2.1
Name: pymeanings
Version: 0.1
Summary: Getting meanings in a GUI dailog box
Home-page: https://github.com/adhrit2019/pymeanings
Author: Adhrit Pramanik
Author-email: adhrit2019@gmail.com
License: MIT
Platform: UNKNOWN
Requires-Dist: PyDictionary
